{
  "current_ui":{"status":"CONFIRMED_UI","server":"horus","url":"laboratory.php","captured_at":"2026-07-18","groups":["basic","high-technology","expert","additional"],"names":["Physics","Chemistry","Mathematics","Astronomy","Espionage","Computer Systems","Ship Armor","Fuel Cells","Jet Engines","Laser","Ion","Plasma","Ecology","Hyperspace","Parallel Universes","Improved Construction","Piercing Attack","Maneuver Defense","Critical Hit","Light Armor","Medium Armor","Heavy Armor"]},
  "historical_help":{"status":"CONFIRMED_HELP","accessed_at":"2026-07-18","urls":{"basic":"https://help.nemexia.com/en_EN/nemexia-new-2379-2425.html","advanced":"https://help.nemexia.com/en_EN/nemexia-new-2379-2426.html","master":"https://help.nemexia.com/en_EN/nemexia-new-2379-2427.html","additional":"https://help.nemexia.com/en_EN/nemexia-new-2379-2428.html"},"shared":{"queue":"one shared research queue across planets","categories":["Basic","Advanced","Master","Additional"],"additional_limit":"one chosen Additional science per player"},"direct_name_matches":[
    {"name":"Physics","category":"Basic","effect":"Energy +5% per level","max_level":10,"requires":["Laboratory/Experimental Facility/Overmind 1"]},
    {"name":"Chemistry","category":"Basic","effect":"Gas fuel -5% per level","max_level":15,"requires":["Laboratory/Experimental Facility/Overmind 3"]},
    {"name":"Mathematics","category":"Basic","effect":"Resource-zone economic output +5% per level","max_level":10,"requires":["Laboratory/Experimental Facility/Overmind 1"]},
    {"name":"Astronomy","category":"Basic","effect":"Ship speed +10% per level","max_level":15,"requires":["Laboratory/Experimental Facility/Overmind 2"]},
    {"name":"Espionage","category":"Advanced","effect":"Improves spying; Help says level 10 reveals attacking ship types/counts","max_level":20,"requires":["Laboratory/Experimental Facility/Overmind 4","Astronomy 2"]},
    {"name":"Fuel Cells","category":"Advanced","effect":"Ship speed +15% per level","max_level":15,"requires":["Laboratory/Experimental Facility/Overmind 6","Chemistry 4"]},
    {"name":"Hyperspace","category":"Master","effect":"Ship speed +20% per level","max_level":15,"requires":["Laboratory/Experimental Facility/Overmind 10","Jet Engines 3"]},
    {"name":"Parallel Universes","category":"Master","effect":"Unlocks master unit construction","max_level":1,"research_time_seconds":3020400,"requires":["Laboratory/Experimental Facility/Overmind 15","Physics 10","Mathematics 10","Astronomy 15","250000 free Energy to start"]},
    {"name":"Light Armor","category":"Master","effect":"Light armor +1% per level","max_level":10,"requires":["Laboratory/Experimental Facility/Overmind 8","Laser science 2"]},
    {"name":"Medium Armor","category":"Master","effect":"Medium armor +2% per level","max_level":10,"requires":["Laboratory/Experimental Facility/Overmind 9","Ion science 2"]},
    {"name":"Heavy Armor","category":"Master","effect":"Heavy armor +3% per level","max_level":10,"requires":["Laboratory/Experimental Facility/Overmind 10","Plasma science 2"]}
  ],"unmapped_current_labels":["Computer Systems","Ship Armor","Jet Engines","Laser","Ion","Plasma","Ecology","Improved Construction","Piercing Attack","Maneuver Defense","Critical Hit"],"mapping_note":"Help uses related but non-identical English labels (e.g. Radar systems, Ship defense, Force attack, Prompt Defense). No direct mapping is asserted without current-card evidence."}
}
